compdeque.py
compressed-deque/__init__.py
compressed-deque/compdeque.py
compressed_deque-0.1.2.dist-info/DESCRIPTION.rst
compressed_deque-0.1.2.dist-info/METADATA
compressed_deque-0.1.2.dist-info/RECORD
compressed_deque-0.1.2.dist-info/WHEEL
compressed_deque-0.1.2.dist-info/metadata.json
compressed_deque-0.1.2.dist-info/top_level.txt
