Metadata-Version: 1.1
Name: compressed-deque
Version: 0.1.2
Summary: Compressed Deque
Home-page: https://github.com/lopespm/compressed-deque
Author: Pedro Lopes
Author-email: UNKNOWN
License: MIT License
